{
  "lastYearRealInMonth": [
    34884,
    16301,
    22167,
    3099,
    6429,
    24557,
    11491,
    21760,
    14270,
    14308,
    18181,
    9335
  ],
  "thisYearPredictInMonth": [
    22288,
    20581,
    24123,
    15709,
    12454,
    16846,
    23867,
    17585,
    14539,
    38516,
    19158,
    35051
  ],
  "thisYearRealInMonth": [
    20663,
    17996,
    11465,
    24899,
    14056,
    28655,
    18080,
    17862,
    27978,
    21983,
    25780,
    10205
  ],
  "lastYearRealInQuarter": [
    73352,
    34085,
    47521,
    41824
  ],
  "thisYearPredictInQuarter": [
    66992,
    45009,
    55991,
    92725
  ],
  "thisYearRealInQuarter": [
    50124,
    67610,
    63920,
    57968
  ]
}